{
  "SplitInGroups_count": {
    "steps": [
      50
    ],
    "timestamps": [
      "2023-10-12T08:42:41.857983"
    ],
    "values": [
      0.03
    ]
  },
  "SplitInGroups_reward": {
    "steps": [
      50
    ],
    "timestamps": [
      "2023-10-12T08:42:41.857983"
    ],
    "values": [
      3e-05
    ]
  },
  "custom_coop_summed_mean": {
    "steps": [
      50
    ],
    "timestamps": [
      "2023-10-12T08:42:41.857983"
    ],
    "values": [
      1.5015
    ]
  },
  "epsilon": {
    "steps": [
      50
    ],
    "timestamps": [
      "2023-10-12T08:42:36.427894"
    ],
    "values": [
      1.0
    ]
  },
  "meta_learner_loss_mean": {
    "steps": [
      50
    ],
    "timestamps": [
      "2023-10-12T08:42:41.857983"
    ],
    "values": [
      0.01093382165489167
    ]
  },
  "meta_learner_prediction_mean": {
    "steps": [
      50
    ],
    "timestamps": [
      "2023-10-12T08:42:41.857983"
    ],
    "values": [
      0.047315622697962405
    ]
  },
  "metric_AverageCooperationLevelMetric": {
    "steps": [
      50
    ],
    "timestamps": [
      "2023-10-12T08:42:41.857983"
    ],
    "values": [
      1.5247524752475248
    ]
  },
  "metric_AverageFoodPerAgentMetric": {
    "steps": [
      50
    ],
    "timestamps": [
      "2023-10-12T08:42:41.857983"
    ],
    "values": [
      1.0482673267326732
    ]
  },
  "metric_EfficiencyMetric": {
    "steps": [
      50
    ],
    "timestamps": [
      "2023-10-12T08:42:41.857983"
    ],
    "values": [
      0.3780286992284798
    ]
  },
  "metric_FoodLeftUncollectedMetric": {
    "steps": [
      50
    ],
    "timestamps": [
      "2023-10-12T08:42:41.857983"
    ],
    "values": [
      4.193069306930693
    ]
  },
  "metric_HighestLevelFoodCollectedMetric": {
    "steps": [
      50
    ],
    "timestamps": [
      "2023-10-12T08:42:41.857983"
    ],
    "values": [
      2.702970297029703
    ]
  },
  "metric_StepsTakenMetric": {
    "steps": [
      50
    ],
    "timestamps": [
      "2023-10-12T08:42:41.857983"
    ],
    "values": [
      0.9900990099009901
    ]
  },
  "metric_TotalFoodCollectedMetric": {
    "steps": [
      50
    ],
    "timestamps": [
      "2023-10-12T08:42:41.857983"
    ],
    "values": [
      4.193069306930693
    ]
  },
  "test_ep_length_mean": {
    "steps": [
      50
    ],
    "timestamps": [
      "2023-10-12T08:42:41.853982"
    ],
    "values": [
      50.0
    ]
  },
  "test_only_built_in_return_mean": {
    "steps": [
      50
    ],
    "timestamps": [
      "2023-10-12T08:42:41.853982"
    ],
    "values": [
      0.0225
    ]
  },
  "test_only_built_in_return_std": {
    "steps": [
      50
    ],
    "timestamps": [
      "2023-10-12T08:42:41.853982"
    ],
    "values": [
      0.08567947375084785
    ]
  },
  "test_only_custom_return_mean": {
    "steps": [
      50
    ],
    "timestamps": [
      "2023-10-12T08:42:41.853982"
    ],
    "values": [
      2.2271131782233713
    ]
  },
  "test_only_custom_return_std": {
    "steps": [
      50
    ],
    "timestamps": [
      "2023-10-12T08:42:41.853982"
    ],
    "values": [
      5.751528008369418
    ]
  },
  "test_summed_return_mean": {
    "steps": [
      50
    ],
    "timestamps": [
      "2023-10-12T08:42:41.853982"
    ],
    "values": [
      2.2496131782233717
    ]
  },
  "test_summed_return_std": {
    "steps": [
      50
    ],
    "timestamps": [
      "2023-10-12T08:42:41.853982"
    ],
    "values": [
      5.751615696430643
    ]
  }
}